pcap_splitter/__init__.py
pcap_splitter/splitter.py
pcap_splitter-1.0.0.dist-info/LICENSE
pcap_splitter-1.0.0.dist-info/METADATA
pcap_splitter-1.0.0.dist-info/WHEEL
pcap_splitter-1.0.0.dist-info/top_level.txt
pcap_splitter-1.0.0.dist-info/RECORD
